pyriesz/__init__.py
pyriesz-0.0.1.dist-info/METADATA
pyriesz-0.0.1.dist-info/WHEEL
pyriesz-0.0.1.dist-info/licenses/LICENSE
pyriesz-0.0.1.dist-info/RECORD
