Metadata-Version: 2.3
Name: PyRiesz
Version: 0.0.1
Summary: Pytorch implementation of the multitasking RieszNet architecture for Auto-DML doubly-robust estimation of causal effects
Project-URL: Homepage, https://github.com/doctor-phil/pyriesz
Project-URL: Issues, https://github.com/doctor-phil/pyriesz/issues
Author-email: Philip Solimine <philipsolimine@gmail.com>
License-File: LICENSE
Classifier: License :: OSI Approved :: MIT License
Classifier: Operating System :: OS Independent
Classifier: Programming Language :: Python :: 3
Requires-Python: >=3.8
